adb_install_cert/__init__.py
adb_install_cert/__main__.py
adb_install_cert/utils.py
adb_install_cert-0.2.2.dist-info/LICENSE
adb_install_cert-0.2.2.dist-info/METADATA
adb_install_cert-0.2.2.dist-info/WHEEL
adb_install_cert-0.2.2.dist-info/entry_points.txt
adb_install_cert-0.2.2.dist-info/RECORD
