Metadata-Version: 2.3
Name: adb-install-cert
Version: 0.2.2
Summary: Install certificates to android system store
License: MIT
Author: sysraccoon
Author-email: sysraccoon@gmail.com
Requires-Python: >=3.10,<4.0
Classifier: License :: OSI Approved :: MIT License
Classifier: Programming Language :: Python :: 3
Classifier: Programming Language :: Python :: 3.10
Classifier: Programming Language :: Python :: 3.11
Classifier: Programming Language :: Python :: 3.12
Classifier: Programming Language :: Python :: 3.13
Requires-Dist: adbutils (>=2.6.1,<3.0.0)
Requires-Dist: click (>=8.1.7,<9.0.0)
